{
    "os": "Linux-5.4.0-172-generic-x86_64-with-glibc2.31",
    "python": "3.10.14",
    "heartbeatAt": "2024-09-08T02:16:42.825668",
    "startedAt": "2024-09-08T02:16:40.329608",
    "docker": null,
    "cuda": null,
    "args": [],
    "state": "running",
    "program": "/data2/common/yuhengtu/workspace/reeval/src/CAT_MLE.py",
    "codePathLocal": "CAT_MLE.py",
    "codePath": "src/CAT_MLE.py",
    "git": {
        "remote": "https://github.com/sangttruong/reeval",
        "commit": "fcfcc7db66b61de2571bc39c159e31fd51e6b13f"
    },
    "email": "yuhengtuece@gmail.com",
    "root": "/data2/common/yuhengtu/workspace/reeval",
    "host": "aisecure-gpu-4",
    "username": "yuhengtu",
    "executable": "/data2/common/yuhengtu/miniconda3/envs/reveal/bin/python",
    "cpu_count": 56,
    "cpu_count_logical": 112,
    "cpu_freq": {
        "current": 3152.550678571428,
        "min": 1000.0,
        "max": 4000.0
    },
    "cpu_freq_per_core": [
        {
            "current": 3233.155,
            "min": 1000.0,
            "max": 4000.0
        },
        {
            "current": 3236.728,
            "min": 1000.0,
            "max": 4000.0
        },
        {
            "current": 2972.264,
            "min": 1000.0,
            "max": 4000.0
        },
        {
            "current": 3233.142,
            "min": 1000.0,
            "max": 4000.0
        },
        {
            "current": 3233.147,
            "min": 1000.0,
            "max": 4000.0
        },
        {
            "current": 3233.142,
            "min": 1000.0,
            "max": 4000.0
        },
        {
            "current": 3233.143,
            "min": 1000.0,
            "max": 4000.0
        },
        {
            "current": 3233.143,
            "min": 1000.0,
            "max": 4000.0
        },
        {
            "current": 3199.22,
            "min": 1000.0,
            "max": 4000.0
        },
        {
            "current": 3233.136,
            "min": 1000.0,
            "max": 4000.0
        },
        {
            "current": 2900.011,
            "min": 1000.0,
            "max": 4000.0
        },
        {
            "current": 2899.978,
            "min": 1000.0,
            "max": 4000.0
        },
        {
            "current": 3233.135,
            "min": 1000.0,
            "max": 4000.0
        },
        {
            "current": 3230.331,
            "min": 1000.0,
            "max": 4000.0
        },
        {
            "current": 3200.423,
            "min": 1000.0,
            "max": 4000.0
        },
        {
            "current": 3230.501,
            "min": 1000.0,
            "max": 4000.0
        },
        {
            "current": 3236.331,
            "min": 1000.0,
            "max": 4000.0
        },
        {
            "current": 3204.722,
            "min": 1000.0,
            "max": 4000.0
        },
        {
            "current": 3230.768,
            "min": 1000.0,
            "max": 4000.0
        },
        {
            "current": 2899.999,
            "min": 1000.0,
            "max": 4000.0
        },
        {
            "current": 3230.929,
            "min": 1000.0,
            "max": 4000.0
        },
        {
            "current": 2900.074,
            "min": 1000.0,
            "max": 4000.0
        },
        {
            "current": 3246.991,
            "min": 1000.0,
            "max": 4000.0
        },
        {
            "current": 3200.123,
            "min": 1000.0,
            "max": 4000.0
        },
        {
            "current": 3231.305,
            "min": 1000.0,
            "max": 4000.0
        },
        {
            "current": 3204.362,
            "min": 1000.0,
            "max": 4000.0
        },
        {
            "current": 2919.832,
            "min": 1000.0,
            "max": 4000.0
        },
        {
            "current": 1192.094,
            "min": 1000.0,
            "max": 4000.0
        },
        {
            "current": 3400.81,
            "min": 1000.0,
            "max": 4000.0
        },
        {
            "current": 3415.726,
            "min": 1000.0,
            "max": 4000.0
        },
        {
            "current": 3247.229,
            "min": 1000.0,
            "max": 4000.0
        },
        {
            "current": 2246.866,
            "min": 1000.0,
            "max": 4000.0
        },
        {
            "current": 1716.397,
            "min": 1000.0,
            "max": 4000.0
        },
        {
            "current": 3399.88,
            "min": 1000.0,
            "max": 4000.0
        },
        {
            "current": 2645.984,
            "min": 1000.0,
            "max": 4000.0
        },
        {
            "current": 3414.062,
            "min": 1000.0,
            "max": 4000.0
        },
        {
            "current": 3414.076,
            "min": 1000.0,
            "max": 4000.0
        },
        {
            "current": 3414.129,
            "min": 1000.0,
            "max": 4000.0
        },
        {
            "current": 3399.896,
            "min": 1000.0,
            "max": 4000.0
        },
        {
            "current": 3414.773,
            "min": 1000.0,
            "max": 4000.0
        },
        {
            "current": 3414.213,
            "min": 1000.0,
            "max": 4000.0
        },
        {
            "current": 3414.267,
            "min": 1000.0,
            "max": 4000.0
        },
        {
            "current": 2804.904,
            "min": 1000.0,
            "max": 4000.0
        },
        {
            "current": 3414.34,
            "min": 1000.0,
            "max": 4000.0
        },
        {
            "current": 3400.002,
            "min": 1000.0,
            "max": 4000.0
        },
        {
            "current": 3285.22,
            "min": 1000.0,
            "max": 4000.0
        },
        {
            "current": 2182.743,
            "min": 1000.0,
            "max": 4000.0
        },
        {
            "current": 1922.489,
            "min": 1000.0,
            "max": 4000.0
        },
        {
            "current": 3414.498,
            "min": 1000.0,
            "max": 4000.0
        },
        {
            "current": 3414.559,
            "min": 1000.0,
            "max": 4000.0
        },
        {
            "current": 3399.304,
            "min": 1000.0,
            "max": 4000.0
        },
        {
            "current": 3414.63,
            "min": 1000.0,
            "max": 4000.0
        },
        {
            "current": 3384.73,
            "min": 1000.0,
            "max": 4000.0
        },
        {
            "current": 3414.706,
            "min": 1000.0,
            "max": 4000.0
        },
        {
            "current": 2907.361,
            "min": 1000.0,
            "max": 4000.0
        },
        {
            "current": 2878.357,
            "min": 1000.0,
            "max": 4000.0
        },
        {
            "current": 3234.847,
            "min": 1000.0,
            "max": 4000.0
        },
        {
            "current": 3234.974,
            "min": 1000.0,
            "max": 4000.0
        },
        {
            "current": 2899.781,
            "min": 1000.0,
            "max": 4000.0
        },
        {
            "current": 3235.559,
            "min": 1000.0,
            "max": 4000.0
        },
        {
            "current": 3249.847,
            "min": 1000.0,
            "max": 4000.0
        },
        {
            "current": 3227.9,
            "min": 1000.0,
            "max": 4000.0
        },
        {
            "current": 3204.968,
            "min": 1000.0,
            "max": 4000.0
        },
        {
            "current": 3235.645,
            "min": 1000.0,
            "max": 4000.0
        },
        {
            "current": 3235.694,
            "min": 1000.0,
            "max": 4000.0
        },
        {
            "current": 3259.012,
            "min": 1000.0,
            "max": 4000.0
        },
        {
            "current": 2899.999,
            "min": 1000.0,
            "max": 4000.0
        },
        {
            "current": 2900.0,
            "min": 1000.0,
            "max": 4000.0
        },
        {
            "current": 3252.623,
            "min": 1000.0,
            "max": 4000.0
        },
        {
            "current": 3251.261,
            "min": 1000.0,
            "max": 4000.0
        },
        {
            "current": 3236.281,
            "min": 1000.0,
            "max": 4000.0
        },
        {
            "current": 3265.245,
            "min": 1000.0,
            "max": 4000.0
        },
        {
            "current": 3236.551,
            "min": 1000.0,
            "max": 4000.0
        },
        {
            "current": 3236.704,
            "min": 1000.0,
            "max": 4000.0
        },
        {
            "current": 3233.638,
            "min": 1000.0,
            "max": 4000.0
        },
        {
            "current": 2900.068,
            "min": 1000.0,
            "max": 4000.0
        },
        {
            "current": 3202.552,
            "min": 1000.0,
            "max": 4000.0
        },
        {
            "current": 2899.999,
            "min": 1000.0,
            "max": 4000.0
        },
        {
            "current": 3237.207,
            "min": 1000.0,
            "max": 4000.0
        },
        {
            "current": 3240.252,
            "min": 1000.0,
            "max": 4000.0
        },
        {
            "current": 3223.49,
            "min": 1000.0,
            "max": 4000.0
        },
        {
            "current": 3237.625,
            "min": 1000.0,
            "max": 4000.0
        },
        {
            "current": 2928.02,
            "min": 1000.0,
            "max": 4000.0
        },
        {
            "current": 1103.04,
            "min": 1000.0,
            "max": 4000.0
        },
        {
            "current": 3414.903,
            "min": 1000.0,
            "max": 4000.0
        },
        {
            "current": 3409.544,
            "min": 1000.0,
            "max": 4000.0
        },
        {
            "current": 3105.431,
            "min": 1000.0,
            "max": 4000.0
        },
        {
            "current": 2261.705,
            "min": 1000.0,
            "max": 4000.0
        },
        {
            "current": 1608.485,
            "min": 1000.0,
            "max": 4000.0
        },
        {
            "current": 3411.797,
            "min": 1000.0,
            "max": 4000.0
        },
        {
            "current": 3068.592,
            "min": 1000.0,
            "max": 4000.0
        },
        {
            "current": 3411.868,
            "min": 1000.0,
            "max": 4000.0
        },
        {
            "current": 3400.007,
            "min": 1000.0,
            "max": 4000.0
        },
        {
            "current": 3400.034,
            "min": 1000.0,
            "max": 4000.0
        },
        {
            "current": 3411.947,
            "min": 1000.0,
            "max": 4000.0
        },
        {
            "current": 3400.011,
            "min": 1000.0,
            "max": 4000.0
        },
        {
            "current": 3399.679,
            "min": 1000.0,
            "max": 4000.0
        },
        {
            "current": 3400.671,
            "min": 1000.0,
            "max": 4000.0
        },
        {
            "current": 2772.013,
            "min": 1000.0,
            "max": 4000.0
        },
        {
            "current": 3404.59,
            "min": 1000.0,
            "max": 4000.0
        },
        {
            "current": 3412.157,
            "min": 1000.0,
            "max": 4000.0
        },
        {
            "current": 3292.604,
            "min": 1000.0,
            "max": 4000.0
        },
        {
            "current": 2132.199,
            "min": 1000.0,
            "max": 4000.0
        },
        {
            "current": 2411.156,
            "min": 1000.0,
            "max": 4000.0
        },
        {
            "current": 3400.015,
            "min": 1000.0,
            "max": 4000.0
        },
        {
            "current": 3412.408,
            "min": 1000.0,
            "max": 4000.0
        },
        {
            "current": 3412.421,
            "min": 1000.0,
            "max": 4000.0
        },
        {
            "current": 3399.97,
            "min": 1000.0,
            "max": 4000.0
        },
        {
            "current": 2950.125,
            "min": 1000.0,
            "max": 4000.0
        },
        {
            "current": 3400.052,
            "min": 1000.0,
            "max": 4000.0
        },
        {
            "current": 2906.264,
            "min": 1000.0,
            "max": 4000.0
        },
        {
            "current": 2446.64,
            "min": 1000.0,
            "max": 4000.0
        }
    ],
    "disk": {
        "/": {
            "total": 3509.423515319824,
            "used": 2652.0653228759766
        }
    },
    "gpu": "NVIDIA RTX A6000",
    "gpu_count": 10,
    "gpu_devices": [
        {
            "name": "NVIDIA RTX A6000",
            "memory_total": 51527024640
        },
        {
            "name": "NVIDIA RTX A6000",
            "memory_total": 51527024640
        },
        {
            "name": "NVIDIA RTX A6000",
            "memory_total": 51527024640
        },
        {
            "name": "NVIDIA RTX A6000",
            "memory_total": 51527024640
        },
        {
            "name": "NVIDIA RTX A6000",
            "memory_total": 51527024640
        },
        {
            "name": "NVIDIA RTX A6000",
            "memory_total": 51527024640
        },
        {
            "name": "NVIDIA RTX A6000",
            "memory_total": 51527024640
        },
        {
            "name": "NVIDIA RTX A6000",
            "memory_total": 51527024640
        },
        {
            "name": "NVIDIA RTX A6000",
            "memory_total": 51527024640
        },
        {
            "name": "NVIDIA RTX A6000",
            "memory_total": 51527024640
        }
    ],
    "memory": {
        "total": 503.54305267333984
    }
}
