{
    "os": "Linux-5.4.0-172-generic-x86_64-with-glibc2.31",
    "python": "3.10.14",
    "heartbeatAt": "2024-09-07T22:40:01.854040",
    "startedAt": "2024-09-07T22:40:00.209813",
    "docker": null,
    "cuda": null,
    "args": [],
    "state": "running",
    "program": "/data2/common/yuhengtu/workspace/reeval/src/CAT_MLE.py",
    "codePathLocal": "CAT_MLE.py",
    "codePath": "src/CAT_MLE.py",
    "git": {
        "remote": "https://github.com/sangttruong/reeval",
        "commit": "fcfcc7db66b61de2571bc39c159e31fd51e6b13f"
    },
    "email": "yuhengtuece@gmail.com",
    "root": "/data2/common/yuhengtu/workspace/reeval",
    "host": "aisecure-gpu-4",
    "username": "yuhengtu",
    "executable": "/data2/common/yuhengtu/miniconda3/envs/reveal/bin/python",
    "cpu_count": 56,
    "cpu_count_logical": 112,
    "cpu_freq": {
        "current": 2474.8227142857136,
        "min": 1000.0,
        "max": 4000.0
    },
    "cpu_freq_per_core": [
        {
            "current": 2234.652,
            "min": 1000.0,
            "max": 4000.0
        },
        {
            "current": 1000.029,
            "min": 1000.0,
            "max": 4000.0
        },
        {
            "current": 3606.92,
            "min": 1000.0,
            "max": 4000.0
        },
        {
            "current": 3606.955,
            "min": 1000.0,
            "max": 4000.0
        },
        {
            "current": 3531.401,
            "min": 1000.0,
            "max": 4000.0
        },
        {
            "current": 3607.085,
            "min": 1000.0,
            "max": 4000.0
        },
        {
            "current": 3607.122,
            "min": 1000.0,
            "max": 4000.0
        },
        {
            "current": 3519.19,
            "min": 1000.0,
            "max": 4000.0
        },
        {
            "current": 1192.902,
            "min": 1000.0,
            "max": 4000.0
        },
        {
            "current": 1000.113,
            "min": 1000.0,
            "max": 4000.0
        },
        {
            "current": 3609.271,
            "min": 1000.0,
            "max": 4000.0
        },
        {
            "current": 1000.857,
            "min": 1000.0,
            "max": 4000.0
        },
        {
            "current": 3532.684,
            "min": 1000.0,
            "max": 4000.0
        },
        {
            "current": 1000.634,
            "min": 1000.0,
            "max": 4000.0
        },
        {
            "current": 1286.306,
            "min": 1000.0,
            "max": 4000.0
        },
        {
            "current": 1593.906,
            "min": 1000.0,
            "max": 4000.0
        },
        {
            "current": 3613.387,
            "min": 1000.0,
            "max": 4000.0
        },
        {
            "current": 1000.196,
            "min": 1000.0,
            "max": 4000.0
        },
        {
            "current": 1397.694,
            "min": 1000.0,
            "max": 4000.0
        },
        {
            "current": 1000.309,
            "min": 1000.0,
            "max": 4000.0
        },
        {
            "current": 1000.219,
            "min": 1000.0,
            "max": 4000.0
        },
        {
            "current": 3614.192,
            "min": 1000.0,
            "max": 4000.0
        },
        {
            "current": 1000.13,
            "min": 1000.0,
            "max": 4000.0
        },
        {
            "current": 3614.212,
            "min": 1000.0,
            "max": 4000.0
        },
        {
            "current": 1000.13,
            "min": 1000.0,
            "max": 4000.0
        },
        {
            "current": 1096.021,
            "min": 1000.0,
            "max": 4000.0
        },
        {
            "current": 1326.962,
            "min": 1000.0,
            "max": 4000.0
        },
        {
            "current": 1248.884,
            "min": 1000.0,
            "max": 4000.0
        },
        {
            "current": 1000.217,
            "min": 1000.0,
            "max": 4000.0
        },
        {
            "current": 3469.533,
            "min": 1000.0,
            "max": 4000.0
        },
        {
            "current": 3469.877,
            "min": 1000.0,
            "max": 4000.0
        },
        {
            "current": 3470.811,
            "min": 1000.0,
            "max": 4000.0
        },
        {
            "current": 3416.982,
            "min": 1000.0,
            "max": 4000.0
        },
        {
            "current": 3472.167,
            "min": 1000.0,
            "max": 4000.0
        },
        {
            "current": 3472.485,
            "min": 1000.0,
            "max": 4000.0
        },
        {
            "current": 3507.534,
            "min": 1000.0,
            "max": 4000.0
        },
        {
            "current": 2913.169,
            "min": 1000.0,
            "max": 4000.0
        },
        {
            "current": 3412.7,
            "min": 1000.0,
            "max": 4000.0
        },
        {
            "current": 2450.389,
            "min": 1000.0,
            "max": 4000.0
        },
        {
            "current": 3513.961,
            "min": 1000.0,
            "max": 4000.0
        },
        {
            "current": 1784.806,
            "min": 1000.0,
            "max": 4000.0
        },
        {
            "current": 3074.471,
            "min": 1000.0,
            "max": 4000.0
        },
        {
            "current": 1520.522,
            "min": 1000.0,
            "max": 4000.0
        },
        {
            "current": 1838.818,
            "min": 1000.0,
            "max": 4000.0
        },
        {
            "current": 3475.884,
            "min": 1000.0,
            "max": 4000.0
        },
        {
            "current": 3475.909,
            "min": 1000.0,
            "max": 4000.0
        },
        {
            "current": 3475.911,
            "min": 1000.0,
            "max": 4000.0
        },
        {
            "current": 3424.334,
            "min": 1000.0,
            "max": 4000.0
        },
        {
            "current": 3233.411,
            "min": 1000.0,
            "max": 4000.0
        },
        {
            "current": 3568.155,
            "min": 1000.0,
            "max": 4000.0
        },
        {
            "current": 3407.785,
            "min": 1000.0,
            "max": 4000.0
        },
        {
            "current": 3397.995,
            "min": 1000.0,
            "max": 4000.0
        },
        {
            "current": 3475.598,
            "min": 1000.0,
            "max": 4000.0
        },
        {
            "current": 3396.687,
            "min": 1000.0,
            "max": 4000.0
        },
        {
            "current": 3475.617,
            "min": 1000.0,
            "max": 4000.0
        },
        {
            "current": 3475.631,
            "min": 1000.0,
            "max": 4000.0
        },
        {
            "current": 2056.563,
            "min": 1000.0,
            "max": 4000.0
        },
        {
            "current": 1000.145,
            "min": 1000.0,
            "max": 4000.0
        },
        {
            "current": 3695.957,
            "min": 1000.0,
            "max": 4000.0
        },
        {
            "current": 3650.993,
            "min": 1000.0,
            "max": 4000.0
        },
        {
            "current": 3624.538,
            "min": 1000.0,
            "max": 4000.0
        },
        {
            "current": 3509.346,
            "min": 1000.0,
            "max": 4000.0
        },
        {
            "current": 3517.605,
            "min": 1000.0,
            "max": 4000.0
        },
        {
            "current": 3627.144,
            "min": 1000.0,
            "max": 4000.0
        },
        {
            "current": 1129.887,
            "min": 1000.0,
            "max": 4000.0
        },
        {
            "current": 1000.195,
            "min": 1000.0,
            "max": 4000.0
        },
        {
            "current": 3515.137,
            "min": 1000.0,
            "max": 4000.0
        },
        {
            "current": 1000.586,
            "min": 1000.0,
            "max": 4000.0
        },
        {
            "current": 3636.029,
            "min": 1000.0,
            "max": 4000.0
        },
        {
            "current": 1000.533,
            "min": 1000.0,
            "max": 4000.0
        },
        {
            "current": 1298.433,
            "min": 1000.0,
            "max": 4000.0
        },
        {
            "current": 1510.13,
            "min": 1000.0,
            "max": 4000.0
        },
        {
            "current": 3653.194,
            "min": 1000.0,
            "max": 4000.0
        },
        {
            "current": 1000.195,
            "min": 1000.0,
            "max": 4000.0
        },
        {
            "current": 1337.317,
            "min": 1000.0,
            "max": 4000.0
        },
        {
            "current": 1000.148,
            "min": 1000.0,
            "max": 4000.0
        },
        {
            "current": 1000.792,
            "min": 1000.0,
            "max": 4000.0
        },
        {
            "current": 3401.033,
            "min": 1000.0,
            "max": 4000.0
        },
        {
            "current": 1000.956,
            "min": 1000.0,
            "max": 4000.0
        },
        {
            "current": 3398.761,
            "min": 1000.0,
            "max": 4000.0
        },
        {
            "current": 1001.344,
            "min": 1000.0,
            "max": 4000.0
        },
        {
            "current": 1047.441,
            "min": 1000.0,
            "max": 4000.0
        },
        {
            "current": 1463.13,
            "min": 1000.0,
            "max": 4000.0
        },
        {
            "current": 1201.094,
            "min": 1000.0,
            "max": 4000.0
        },
        {
            "current": 1000.052,
            "min": 1000.0,
            "max": 4000.0
        },
        {
            "current": 3582.405,
            "min": 1000.0,
            "max": 4000.0
        },
        {
            "current": 3563.98,
            "min": 1000.0,
            "max": 4000.0
        },
        {
            "current": 3516.539,
            "min": 1000.0,
            "max": 4000.0
        },
        {
            "current": 3480.216,
            "min": 1000.0,
            "max": 4000.0
        },
        {
            "current": 3479.08,
            "min": 1000.0,
            "max": 4000.0
        },
        {
            "current": 3463.04,
            "min": 1000.0,
            "max": 4000.0
        },
        {
            "current": 3477.526,
            "min": 1000.0,
            "max": 4000.0
        },
        {
            "current": 3221.76,
            "min": 1000.0,
            "max": 4000.0
        },
        {
            "current": 3477.992,
            "min": 1000.0,
            "max": 4000.0
        },
        {
            "current": 3100.499,
            "min": 1000.0,
            "max": 4000.0
        },
        {
            "current": 3479.123,
            "min": 1000.0,
            "max": 4000.0
        },
        {
            "current": 1652.424,
            "min": 1000.0,
            "max": 4000.0
        },
        {
            "current": 2746.852,
            "min": 1000.0,
            "max": 4000.0
        },
        {
            "current": 1776.464,
            "min": 1000.0,
            "max": 4000.0
        },
        {
            "current": 1761.5,
            "min": 1000.0,
            "max": 4000.0
        },
        {
            "current": 3571.678,
            "min": 1000.0,
            "max": 4000.0
        },
        {
            "current": 3571.795,
            "min": 1000.0,
            "max": 4000.0
        },
        {
            "current": 3465.154,
            "min": 1000.0,
            "max": 4000.0
        },
        {
            "current": 3478.949,
            "min": 1000.0,
            "max": 4000.0
        },
        {
            "current": 2967.638,
            "min": 1000.0,
            "max": 4000.0
        },
        {
            "current": 3478.472,
            "min": 1000.0,
            "max": 4000.0
        },
        {
            "current": 3478.459,
            "min": 1000.0,
            "max": 4000.0
        },
        {
            "current": 3478.381,
            "min": 1000.0,
            "max": 4000.0
        },
        {
            "current": 3392.572,
            "min": 1000.0,
            "max": 4000.0
        },
        {
            "current": 3478.242,
            "min": 1000.0,
            "max": 4000.0
        },
        {
            "current": 3580.234,
            "min": 1000.0,
            "max": 4000.0
        },
        {
            "current": 3498.047,
            "min": 1000.0,
            "max": 4000.0
        }
    ],
    "disk": {
        "/": {
            "total": 3509.423515319824,
            "used": 2652.092842102051
        }
    },
    "gpu": "NVIDIA RTX A6000",
    "gpu_count": 10,
    "gpu_devices": [
        {
            "name": "NVIDIA RTX A6000",
            "memory_total": 51527024640
        },
        {
            "name": "NVIDIA RTX A6000",
            "memory_total": 51527024640
        },
        {
            "name": "NVIDIA RTX A6000",
            "memory_total": 51527024640
        },
        {
            "name": "NVIDIA RTX A6000",
            "memory_total": 51527024640
        },
        {
            "name": "NVIDIA RTX A6000",
            "memory_total": 51527024640
        },
        {
            "name": "NVIDIA RTX A6000",
            "memory_total": 51527024640
        },
        {
            "name": "NVIDIA RTX A6000",
            "memory_total": 51527024640
        },
        {
            "name": "NVIDIA RTX A6000",
            "memory_total": 51527024640
        },
        {
            "name": "NVIDIA RTX A6000",
            "memory_total": 51527024640
        },
        {
            "name": "NVIDIA RTX A6000",
            "memory_total": 51527024640
        }
    ],
    "memory": {
        "total": 503.54305267333984
    }
}
