{
    "os": "Linux-5.4.0-172-generic-x86_64-with-glibc2.31",
    "python": "3.10.14",
    "heartbeatAt": "2024-09-07T22:42:00.811558",
    "startedAt": "2024-09-07T22:42:00.537797",
    "docker": null,
    "cuda": null,
    "args": [],
    "state": "running",
    "program": "/data2/common/yuhengtu/workspace/reeval/src/CAT_MLE.py",
    "codePathLocal": "CAT_MLE.py",
    "codePath": "src/CAT_MLE.py",
    "git": {
        "remote": "https://github.com/sangttruong/reeval",
        "commit": "fcfcc7db66b61de2571bc39c159e31fd51e6b13f"
    },
    "email": "yuhengtuece@gmail.com",
    "root": "/data2/common/yuhengtu/workspace/reeval",
    "host": "aisecure-gpu-4",
    "username": "yuhengtu",
    "executable": "/data2/common/yuhengtu/miniconda3/envs/reveal/bin/python",
    "cpu_count": 56,
    "cpu_count_logical": 112,
    "cpu_freq": {
        "current": 3193.4629821428603,
        "min": 1000.0,
        "max": 4000.0
    },
    "cpu_freq_per_core": [
        {
            "current": 3399.999,
            "min": 1000.0,
            "max": 4000.0
        },
        {
            "current": 3400.0,
            "min": 1000.0,
            "max": 4000.0
        },
        {
            "current": 3400.0,
            "min": 1000.0,
            "max": 4000.0
        },
        {
            "current": 3400.0,
            "min": 1000.0,
            "max": 4000.0
        },
        {
            "current": 2699.999,
            "min": 1000.0,
            "max": 4000.0
        },
        {
            "current": 3399.999,
            "min": 1000.0,
            "max": 4000.0
        },
        {
            "current": 3399.999,
            "min": 1000.0,
            "max": 4000.0
        },
        {
            "current": 3399.997,
            "min": 1000.0,
            "max": 4000.0
        },
        {
            "current": 2699.998,
            "min": 1000.0,
            "max": 4000.0
        },
        {
            "current": 2700.0,
            "min": 1000.0,
            "max": 4000.0
        },
        {
            "current": 3400.001,
            "min": 1000.0,
            "max": 4000.0
        },
        {
            "current": 3400.266,
            "min": 1000.0,
            "max": 4000.0
        },
        {
            "current": 3400.0,
            "min": 1000.0,
            "max": 4000.0
        },
        {
            "current": 3399.999,
            "min": 1000.0,
            "max": 4000.0
        },
        {
            "current": 3400.0,
            "min": 1000.0,
            "max": 4000.0
        },
        {
            "current": 2700.0,
            "min": 1000.0,
            "max": 4000.0
        },
        {
            "current": 2699.999,
            "min": 1000.0,
            "max": 4000.0
        },
        {
            "current": 3400.0,
            "min": 1000.0,
            "max": 4000.0
        },
        {
            "current": 3399.999,
            "min": 1000.0,
            "max": 4000.0
        },
        {
            "current": 3400.0,
            "min": 1000.0,
            "max": 4000.0
        },
        {
            "current": 2700.0,
            "min": 1000.0,
            "max": 4000.0
        },
        {
            "current": 3400.0,
            "min": 1000.0,
            "max": 4000.0
        },
        {
            "current": 3400.0,
            "min": 1000.0,
            "max": 4000.0
        },
        {
            "current": 2699.997,
            "min": 1000.0,
            "max": 4000.0
        },
        {
            "current": 1881.594,
            "min": 1000.0,
            "max": 4000.0
        },
        {
            "current": 3399.999,
            "min": 1000.0,
            "max": 4000.0
        },
        {
            "current": 3400.0,
            "min": 1000.0,
            "max": 4000.0
        },
        {
            "current": 3262.833,
            "min": 1000.0,
            "max": 4000.0
        },
        {
            "current": 3110.326,
            "min": 1000.0,
            "max": 4000.0
        },
        {
            "current": 1413.048,
            "min": 1000.0,
            "max": 4000.0
        },
        {
            "current": 3394.425,
            "min": 1000.0,
            "max": 4000.0
        },
        {
            "current": 3396.863,
            "min": 1000.0,
            "max": 4000.0
        },
        {
            "current": 3399.999,
            "min": 1000.0,
            "max": 4000.0
        },
        {
            "current": 3399.999,
            "min": 1000.0,
            "max": 4000.0
        },
        {
            "current": 2241.575,
            "min": 1000.0,
            "max": 4000.0
        },
        {
            "current": 2609.567,
            "min": 1000.0,
            "max": 4000.0
        },
        {
            "current": 3399.999,
            "min": 1000.0,
            "max": 4000.0
        },
        {
            "current": 3400.0,
            "min": 1000.0,
            "max": 4000.0
        },
        {
            "current": 3399.999,
            "min": 1000.0,
            "max": 4000.0
        },
        {
            "current": 2699.968,
            "min": 1000.0,
            "max": 4000.0
        },
        {
            "current": 3400.0,
            "min": 1000.0,
            "max": 4000.0
        },
        {
            "current": 3400.003,
            "min": 1000.0,
            "max": 4000.0
        },
        {
            "current": 3400.0,
            "min": 1000.0,
            "max": 4000.0
        },
        {
            "current": 3399.999,
            "min": 1000.0,
            "max": 4000.0
        },
        {
            "current": 3401.625,
            "min": 1000.0,
            "max": 4000.0
        },
        {
            "current": 3399.999,
            "min": 1000.0,
            "max": 4000.0
        },
        {
            "current": 3400.05,
            "min": 1000.0,
            "max": 4000.0
        },
        {
            "current": 2291.005,
            "min": 1000.0,
            "max": 4000.0
        },
        {
            "current": 2699.998,
            "min": 1000.0,
            "max": 4000.0
        },
        {
            "current": 3400.0,
            "min": 1000.0,
            "max": 4000.0
        },
        {
            "current": 2705.581,
            "min": 1000.0,
            "max": 4000.0
        },
        {
            "current": 3400.0,
            "min": 1000.0,
            "max": 4000.0
        },
        {
            "current": 2700.0,
            "min": 1000.0,
            "max": 4000.0
        },
        {
            "current": 3396.621,
            "min": 1000.0,
            "max": 4000.0
        },
        {
            "current": 3351.834,
            "min": 1000.0,
            "max": 4000.0
        },
        {
            "current": 3400.0,
            "min": 1000.0,
            "max": 4000.0
        },
        {
            "current": 3399.997,
            "min": 1000.0,
            "max": 4000.0
        },
        {
            "current": 3399.999,
            "min": 1000.0,
            "max": 4000.0
        },
        {
            "current": 3399.999,
            "min": 1000.0,
            "max": 4000.0
        },
        {
            "current": 3399.999,
            "min": 1000.0,
            "max": 4000.0
        },
        {
            "current": 2700.0,
            "min": 1000.0,
            "max": 4000.0
        },
        {
            "current": 3399.997,
            "min": 1000.0,
            "max": 4000.0
        },
        {
            "current": 3400.0,
            "min": 1000.0,
            "max": 4000.0
        },
        {
            "current": 3400.001,
            "min": 1000.0,
            "max": 4000.0
        },
        {
            "current": 2699.999,
            "min": 1000.0,
            "max": 4000.0
        },
        {
            "current": 2700.0,
            "min": 1000.0,
            "max": 4000.0
        },
        {
            "current": 3399.999,
            "min": 1000.0,
            "max": 4000.0
        },
        {
            "current": 3400.0,
            "min": 1000.0,
            "max": 4000.0
        },
        {
            "current": 3400.0,
            "min": 1000.0,
            "max": 4000.0
        },
        {
            "current": 3400.003,
            "min": 1000.0,
            "max": 4000.0
        },
        {
            "current": 3400.0,
            "min": 1000.0,
            "max": 4000.0
        },
        {
            "current": 2777.836,
            "min": 1000.0,
            "max": 4000.0
        },
        {
            "current": 2700.0,
            "min": 1000.0,
            "max": 4000.0
        },
        {
            "current": 3400.0,
            "min": 1000.0,
            "max": 4000.0
        },
        {
            "current": 3400.001,
            "min": 1000.0,
            "max": 4000.0
        },
        {
            "current": 3399.997,
            "min": 1000.0,
            "max": 4000.0
        },
        {
            "current": 2699.999,
            "min": 1000.0,
            "max": 4000.0
        },
        {
            "current": 3400.0,
            "min": 1000.0,
            "max": 4000.0
        },
        {
            "current": 3399.998,
            "min": 1000.0,
            "max": 4000.0
        },
        {
            "current": 2699.991,
            "min": 1000.0,
            "max": 4000.0
        },
        {
            "current": 1909.705,
            "min": 1000.0,
            "max": 4000.0
        },
        {
            "current": 3399.999,
            "min": 1000.0,
            "max": 4000.0
        },
        {
            "current": 3399.996,
            "min": 1000.0,
            "max": 4000.0
        },
        {
            "current": 3398.729,
            "min": 1000.0,
            "max": 4000.0
        },
        {
            "current": 3186.401,
            "min": 1000.0,
            "max": 4000.0
        },
        {
            "current": 1338.455,
            "min": 1000.0,
            "max": 4000.0
        },
        {
            "current": 3400.0,
            "min": 1000.0,
            "max": 4000.0
        },
        {
            "current": 3069.026,
            "min": 1000.0,
            "max": 4000.0
        },
        {
            "current": 3400.0,
            "min": 1000.0,
            "max": 4000.0
        },
        {
            "current": 3400.0,
            "min": 1000.0,
            "max": 4000.0
        },
        {
            "current": 2506.32,
            "min": 1000.0,
            "max": 4000.0
        },
        {
            "current": 2467.574,
            "min": 1000.0,
            "max": 4000.0
        },
        {
            "current": 3399.997,
            "min": 1000.0,
            "max": 4000.0
        },
        {
            "current": 3400.003,
            "min": 1000.0,
            "max": 4000.0
        },
        {
            "current": 3399.999,
            "min": 1000.0,
            "max": 4000.0
        },
        {
            "current": 2699.998,
            "min": 1000.0,
            "max": 4000.0
        },
        {
            "current": 3398.915,
            "min": 1000.0,
            "max": 4000.0
        },
        {
            "current": 3400.0,
            "min": 1000.0,
            "max": 4000.0
        },
        {
            "current": 3400.0,
            "min": 1000.0,
            "max": 4000.0
        },
        {
            "current": 3399.997,
            "min": 1000.0,
            "max": 4000.0
        },
        {
            "current": 3400.0,
            "min": 1000.0,
            "max": 4000.0
        },
        {
            "current": 3400.001,
            "min": 1000.0,
            "max": 4000.0
        },
        {
            "current": 3399.999,
            "min": 1000.0,
            "max": 4000.0
        },
        {
            "current": 2940.935,
            "min": 1000.0,
            "max": 4000.0
        },
        {
            "current": 2699.999,
            "min": 1000.0,
            "max": 4000.0
        },
        {
            "current": 3399.998,
            "min": 1000.0,
            "max": 4000.0
        },
        {
            "current": 2711.218,
            "min": 1000.0,
            "max": 4000.0
        },
        {
            "current": 3399.644,
            "min": 1000.0,
            "max": 4000.0
        },
        {
            "current": 2699.999,
            "min": 1000.0,
            "max": 4000.0
        },
        {
            "current": 3400.0,
            "min": 1000.0,
            "max": 4000.0
        },
        {
            "current": 3278.907,
            "min": 1000.0,
            "max": 4000.0
        },
        {
            "current": 3399.999,
            "min": 1000.0,
            "max": 4000.0
        }
    ],
    "disk": {
        "/": {
            "total": 3509.423515319824,
            "used": 2652.092727661133
        }
    },
    "gpu": "NVIDIA RTX A6000",
    "gpu_count": 10,
    "gpu_devices": [
        {
            "name": "NVIDIA RTX A6000",
            "memory_total": 51527024640
        },
        {
            "name": "NVIDIA RTX A6000",
            "memory_total": 51527024640
        },
        {
            "name": "NVIDIA RTX A6000",
            "memory_total": 51527024640
        },
        {
            "name": "NVIDIA RTX A6000",
            "memory_total": 51527024640
        },
        {
            "name": "NVIDIA RTX A6000",
            "memory_total": 51527024640
        },
        {
            "name": "NVIDIA RTX A6000",
            "memory_total": 51527024640
        },
        {
            "name": "NVIDIA RTX A6000",
            "memory_total": 51527024640
        },
        {
            "name": "NVIDIA RTX A6000",
            "memory_total": 51527024640
        },
        {
            "name": "NVIDIA RTX A6000",
            "memory_total": 51527024640
        },
        {
            "name": "NVIDIA RTX A6000",
            "memory_total": 51527024640
        }
    ],
    "memory": {
        "total": 503.54305267333984
    }
}
